huputs/__init__.py
huputs/errors.py
huputs/ex.py
huputs/system.py
huputs/utils.py
huputs-0.1.1.dist-info/LICENSE
huputs-0.1.1.dist-info/METADATA
huputs-0.1.1.dist-info/WHEEL
huputs-0.1.1.dist-info/top_level.txt
huputs-0.1.1.dist-info/RECORD
