Metadata-Version: 2.1
Name: huputs
Version: 0.1.1
Summary: Human-Understandable Python Unit Test System
Home-page: https://github.com/windowsboy111/huputs
Author: windowsboy111
Author-email: wboy111@outlook.com
License: MIT
Platform: UNKNOWN
Classifier: License :: OSI Approved :: MIT License
Classifier: Programming Language :: Python :: 3
Classifier: Programming Language :: Python :: 3.7
Classifier: Programming Language :: Python :: 3.8
Classifier: Programming Language :: Python :: 3.9
License-File: LICENSE
Requires-Dist: colorama
